[ {
  "num" : "0",
  "question" : "",
  "answer" : "그리스",
  "country" : "그리스.png",
  "capital" : null
}, {
  "num" : "1",
  "question" : "",
  "answer" : "남아프리카공화국",
  "country" : "남아프리카공화국.png",
  "capital" : null
}, {
  "num" : "2",
  "question" : "",
  "answer" : "네덜란드",
  "country" : "네덜란드.png",
  "capital" : null
}, {
  "num" : "3",
  "question" : "",
  "answer" : "뉴질랜드",
  "country" : "뉴질랜드.png",
  "capital" : null
}, {
  "num" : "4",
  "question" : "",
  "answer" : "대한민국",
  "country" : "대한민국.png",
  "capital" : null
}, {
  "num" : "5",
  "question" : "",
  "answer" : "독일",
  "country" : "독일.png",
  "capital" : null
}, {
  "num" : "6",
  "question" : "",
  "answer" : "러시아",
  "country" : "러시아.png",
  "capital" : null
}, {
  "num" : "7",
  "question" : "",
  "answer" : "멕시코",
  "country" : "멕시코.png",
  "capital" : null
}, {
  "num" : "8",
  "question" : "",
  "answer" : "미국",
  "country" : "미국.png",
  "capital" : null
}, {
  "num" : "9",
  "question" : "",
  "answer" : "베트남",
  "country" : "베트남.png",
  "capital" : null
}, {
  "num" : "10",
  "question" : "",
  "answer" : "브라질",
  "country" : "브라질.png",
  "capital" : null
}, {
  "num" : "11",
  "question" : "",
  "answer" : "사우디아라비아",
  "country" : "사우디아라비아.png",
  "capital" : null
}, {
  "num" : "12",
  "question" : "",
  "answer" : "스웨덴",
  "country" : "스웨덴.png",
  "capital" : null
}, {
  "num" : "13",
  "question" : "",
  "answer" : "스위스",
  "country" : "스위스.png",
  "capital" : null
}, {
  "num" : "14",
  "question" : "",
  "answer" : "스페인",
  "country" : "스페인.png",
  "capital" : null
}, {
  "num" : "15",
  "question" : "",
  "answer" : "아랍에미리트",
  "country" : "아랍에미리트.png",
  "capital" : null
}, {
  "num" : "16",
  "question" : "",
  "answer" : "아르헨티나",
  "country" : "아르헨티나.png",
  "capital" : null
}, {
  "num" : "17",
  "question" : "",
  "answer" : "영국",
  "country" : "영국.png",
  "capital" : null
}, {
  "num" : "18",
  "question" : "",
  "answer" : "이란",
  "country" : "이란.png",
  "capital" : null
}, {
  "num" : "19",
  "question" : "",
  "answer" : "이스라엘",
  "country" : "이스라엘.png",
  "capital" : null
}, {
  "num" : "20",
  "question" : "",
  "answer" : "이집트",
  "country" : "이집트.png",
  "capital" : null
}, {
  "num" : "21",
  "question" : "",
  "answer" : "이탈리아",
  "country" : "이탈리아.png",
  "capital" : null
}, {
  "num" : "22",
  "question" : "",
  "answer" : "인도",
  "country" : "인도.png",
  "capital" : null
}, {
  "num" : "23",
  "question" : "",
  "answer" : "인도네시아",
  "country" : "인도네시아.png",
  "capital" : null
}, {
  "num" : "24",
  "question" : "",
  "answer" : "일본",
  "country" : "일본.png",
  "capital" : null
}, {
  "num" : "25",
  "question" : "",
  "answer" : "중국",
  "country" : "중국.png",
  "capital" : null
}, {
  "num" : "26",
  "question" : "",
  "answer" : "캐나다",
  "country" : "캐나다.png",
  "capital" : null
}, {
  "num" : "27",
  "question" : "",
  "answer" : "태국",
  "country" : "태국.png",
  "capital" : null
}, {
  "num" : "28",
  "question" : "",
  "answer" : "튀르키예",
  "country" : "튀르키예.png",
  "capital" : null
}, {
  "num" : "29",
  "question" : "",
  "answer" : "폴란드",
  "country" : "폴란드.png",
  "capital" : null
}, {
  "num" : "30",
  "question" : "",
  "answer" : "프랑스",
  "country" : "프랑스.png",
  "capital" : null
}, {
  "num" : "31",
  "question" : "",
  "answer" : "필리핀",
  "country" : "필리핀.png",
  "capital" : null
}, {
  "num" : "32",
  "question" : "",
  "answer" : "호주",
  "country" : "호주.png",
  "capital" : null
} ]